Workbook

Sheet INDEX
A1: Comparable Transactions (PTM) — Teaching Pack (5 Cases)
A3: Case | B3: Sheet | C3: Learning point | D3: Open
A4: Case 1 | B4: CASE_1_ControlPremium_100pct | C4: Learning point: EV/EBITDA from 100% acquisitions reflects control premium. | D4: Open
A5: Case 2 | B5: CASE_2_DealSelection_Include01 | C5: Learning point: Use Deal Type + Include (0/1) to screen transactions before averaging multiples. | D5: Open
A6: Case 3 | B6: CASE_3_AvgVsMedian_Outliers | C6: Learning point: Average can be pulled by high-multiple outliers; median is more robust. | D6: Open
A7: Case 4 | B7: CASE_4_PartialStake_Normalization | C7: Learning point: Scale partial stake deal values to 100% equity before computing EV multiples. | D7: Open
A8: Case 5 | B8: CASE_5_Judgment_Integrated | C8: Learning point: PTM requires judgment: select deals, compute multiples, interpret outputs. | D8: Open
A11: Legend:
A12: Inputs | B12: Calculations | C12: Outputs
A14: Instruction: In each case sheet, set Include? = 1 for deals you want to use; 0 to exclude.

Sheet CASE_1_ControlPremium_100pct
A1: CASE 1 — Control Premium Embedded in 100% Acquisitions
N2: ⬅ Back to INDEX
A3: Learning point: EV/EBITDA from 100% acquisitions reflects control premium.
A5: SECTION A — Comparable Transactions (Inputs)
A6: Deal Ref | B6: Acquirer | C6: Target | D6: Deal Type | E6: Stake % | F6: Deal Value (₹ cr) | G6: Revenue (₹ cr) | H6: EBITDA (₹ cr) | I6: Net Debt (₹ cr) | J6: Include? (0/1) | K6: Equity Value @100% (₹ cr) | L6: Enterprise Value (₹ cr) | M6: EV/Revenue | N6: EV/EBITDA
A7: D01 | B7: Tata Engineering Ltd. | C7: Prakash Gears Pvt. Ltd. | D7: 100% Acquisition | E7: 1 | F7: 2400 | G7: 1950 | H7: 260 | I7: 480 | J7: 1 | K7: =IF(J7=1,F7/(E7),"") | L7: =IF(J7=1,K7+I7,"") | M7: =IF(J7=1,L7/G7,"") | N7: =IF(J7=1,L7/H7,"")
A8: D02 | B8: Mahindra Mobility Ltd. | C8: Orion Axles Pvt. Ltd. | D8: 100% Acquisition | E8: 1 | F8: 3200 | G8: 2450 | H8: 310 | I8: 520 | J8: 1 | K8: =IF(J8=1,F8/(E8),"") | L8: =IF(J8=1,K8+I8,"") | M8: =IF(J8=1,L8/G8,"") | N8: =IF(J8=1,L8/H8,"")
A9: D03 | B9: Bajaj Auto Systems | C9: Velocity Motors Pvt. Ltd. | D9: 100% Acquisition | E9: 1 | F9: 1800 | G9: 1420 | H9: 190 | I9: 350 | J9: 1 | K9: =IF(J9=1,F9/(E9),"") | L9: =IF(J9=1,K9+I9,"") | M9: =IF(J9=1,L9/G9,"") | N9: =IF(J9=1,L9/H9,"")
A10: D04 | B10: TVS Auto Ltd. | C10: Supreme Drives Pvt. Ltd. | D10: 100% Acquisition | E10: 1 | F10: 2750 | G10: 2100 | H10: 280 | I10: 460 | J10: 1 | K10: =IF(J10=1,F10/(E10),"") | L10: =IF(J10=1,K10+I10,"") | M10: =IF(J10=1,L10/G10,"") | N10: =IF(J10=1,L10/H10,"")
A11: D05 | B11: Hero Engineering | C11: Alpha Components Pvt. Ltd. | D11: 100% Acquisition | E11: 1 | F11: 3500 | G11: 2700 | H11: 340 | I11: 600 | J11: 1 | K11: =IF(J11=1,F11/(E11),"") | L11: =IF(J11=1,K11+I11,"") | M11: =IF(J11=1,L11/G11,"") | N11: =IF(J11=1,L11/H11,"")
A12: D06 | B12: Ashok Leyland Engg. | C12: Nova Auto Parts Pvt. Ltd. | D12: 100% Acquisition | E12: 1 | F12: 1650 | G12: 1300 | H12: 170 | I12: 300 | J12: 1 | K12: =IF(J12=1,F12/(E12),"") | L12: =IF(J12=1,K12+I12,"") | M12: =IF(J12=1,L12/G12,"") | N12: =IF(J12=1,L12/H12,"")
A13: D07 | B13: Eicher Motors | C13: Precision Wheels Pvt. Ltd. | D13: 100% Acquisition | E13: 1 | F13: 2200 | G13: 1750 | H13: 230 | I13: 410 | J13: 1 | K13: =IF(J13=1,F13/(E13),"") | L13: =IF(J13=1,K13+I13,"") | M13: =IF(J13=1,L13/G13,"") | N13: =IF(J13=1,L13/H13,"")
A14: D08 | B14: Sona Mobility Ltd. | C14: Apex Transmissions Pvt. Ltd. | D14: 100% Acquisition | E14: 1 | F14: 2950 | G14: 2250 | H14: 300 | I14: 510 | J14: 1 | K14: =IF(J14=1,F14/(E14),"") | L14: =IF(J14=1,K14+I14,"") | M14: =IF(J14=1,L14/G14,"") | N14: =IF(J14=1,L14/H14,"")
A16: SECTION B — Descriptive Statistics (Selected Deals Only)
A17: Average EV/EBITDA | B17: =AVERAGEIF(J7:J14,1,N7:N14) | D17: Included deals (count) | E17: =COUNTIF(J7:J14,1)
A18: Median EV/EBITDA
A20: SECTION C — Target Company Valuation (Using EV/EBITDA)
A21: Target Company | B21: Shakti Auto Components Pvt. Ltd. | D21: Using Average Multiple | G21: Using Median Multiple
A22: Target EBITDA (₹ cr) | B22: 180 | D22: Implied EV (₹ cr) | E22: =B17*B22 | G22: Implied EV (₹ cr) | H22: =B18*B22
A23: Target Net Debt (₹ cr) | B23: 420 | D23: Implied Equity Value (₹ cr) | E23: =E22-B23 | G23: Implied Equity Value (₹ cr) | H23: =H22-B23
A24: Shares Outstanding (cr) | B24: 12 | D24: Implied Price per Share (₹) | E24: =(E23)/(B24) | G24: Implied Price per Share (₹) | H24: =(H23)/(B24)
A26: SECTION D — Checks
A27: Check 1: At least 3 deals included | B27: =IF(E17>=3,"PASS","FAIL") | D27: Case Status | E27: =IF(AND(B27="PASS",B28="PASS",B29="PASS"),"PASS","FAIL")
A28: Check 2: No DIV/0! in EV/EBITDA | B28: =IF(COUNTIF(N7:N14,"#DIV/0!")=0,"PASS","FAIL")
A29: Check 3: Included stakes between 0% and 100% | B29: =IF(SUMPRODUCT(--(J7:J14=1),--((E7:E14<=0)+(E7:E14>1)))=0,"PASS","FAIL")
A31: ⬅ Back to INDEX

Sheet CASE_2_DealSelection_Include01
A1: CASE 2 — Deal Selection Using Transaction Characteristics
N2: ⬅ Back to INDEX
A3: Learning point: Use Deal Type + Include (0/1) to screen transactions before averaging multiples.
A5: SECTION A — Comparable Transactions (Inputs)
A6: Deal Ref | B6: Acquirer | C6: Target | D6: Deal Type | E6: Stake % | F6: Deal Value (₹ cr) | G6: Revenue (₹ cr) | H6: EBITDA (₹ cr) | I6: Net Debt (₹ cr) | J6: Include? (0/1) | K6: Equity Value @100% (₹ cr) | L6: Enterprise Value (₹ cr) | M6: EV/Revenue | N6: EV/EBITDA
A7: D01 | B7: Reliance Retail | C7: CityMart Pvt. Ltd. | D7: Strategic Acquisition | E7: 1 | F7: 1200 | G7: 1050 | H7: 120 | I7: 200 | J7: 1 | K7: =IF(J7=1,F7/(E7),"") | L7: =IF(J7=1,K7+I7,"") | M7: =IF(J7=1,L7/G7,"") | N7: =IF(J7=1,L7/H7,"")
A8: D02 | B8: Avenue Supermarts | C8: FreshBasket Pvt. Ltd. | D8: Majority Stake | E8: 0.6 | F8: 950 | G8: 980 | H8: 110 | I8: 180 | J8: 1 | K8: =IF(J8=1,F8/(E8),"") | L8: =IF(J8=1,K8+I8,"") | M8: =IF(J8=1,L8/G8,"") | N8: =IF(J8=1,L8/H8,"")
A9: D03 | B9: Future Ventures | C9: ValueShop Pvt. Ltd. | D9: Minority Stake | E9: 0.45 | F9: 700 | G9: 820 | H9: 95 | I9: 160 | J9: 1 | K9: =IF(J9=1,F9/(E9),"") | L9: =IF(J9=1,K9+I9,"") | M9: =IF(J9=1,L9/G9,"") | N9: =IF(J9=1,L9/H9,"")
A10: D04 | B10: Tata Consumer Retail | C10: UrbanNeeds Pvt. Ltd. | D10: Strategic Acquisition | E10: 1 | F10: 1500 | G10: 1300 | H10: 150 | I10: 260 | J10: 1 | K10: =IF(J10=1,F10/(E10),"") | L10: =IF(J10=1,K10+I10,"") | M10: =IF(J10=1,L10/G10,"") | N10: =IF(J10=1,L10/H10,"")
A11: D05 | B11: KKR India | C11: MegaRetail Pvt. Ltd. | D11: Leveraged Buyout (LBO) | E11: 0.75 | F11: 1100 | G11: 1000 | H11: 130 | I11: 220 | J11: 1 | K11: =IF(J11=1,F11/(E11),"") | L11: =IF(J11=1,K11+I11,"") | M11: =IF(J11=1,L11/G11,"") | N11: =IF(J11=1,L11/H11,"")
A12: D06 | B12: Aditya Birla Retail | C12: DailyChoice Pvt. Ltd. | D12: Strategic Acquisition | E12: 1 | F12: 850 | G12: 900 | H12: 100 | I12: 170 | J12: 1 | K12: =IF(J12=1,F12/(E12),"") | L12: =IF(J12=1,K12+I12,"") | M12: =IF(J12=1,L12/G12,"") | N12: =IF(J12=1,L12/H12,"")
A13: D07 | B13: Amazon India | C13: QuickBuy Pvt. Ltd. | D13: Strategic Acquisition | E13: 1 | F13: 1400 | G13: 1200 | H13: 140 | I13: 240 | J13: 1 | K13: =IF(J13=1,F13/(E13),"") | L13: =IF(J13=1,K13+I13,"") | M13: =IF(J13=1,L13/G13,"") | N13: =IF(J13=1,L13/H13,"")
A14: D08 | B14: Flipkart Group | C14: EasyShop Pvt. Ltd. | D14: Deal Incomplete | E14: 0.5 | F14: 780 | G14: 860 | H14: 105 | I14: 190 | J14: 1 | K14: =IF(J14=1,F14/(E14),"") | L14: =IF(J14=1,K14+I14,"") | M14: =IF(J14=1,L14/G14,"") | N14: =IF(J14=1,L14/H14,"")
A16: SECTION B — Descriptive Statistics (Selected Deals Only)
A17: Average EV/EBITDA | B17: =AVERAGEIF(J7:J14,1,N7:N14) | D17: Included deals (count) | E17: =COUNTIF(J7:J14,1)
A18: Median EV/EBITDA
A20: SECTION C — Target Company Valuation (Using EV/EBITDA)
A21: Target Company | B21: LMN Stores Pvt. Ltd. | D21: Using Average Multiple | G21: Using Median Multiple
A22: Target EBITDA (₹ cr) | B22: 95 | D22: Implied EV (₹ cr) | E22: =B17*B22 | G22: Implied EV (₹ cr) | H22: =B18*B22
A23: Target Net Debt (₹ cr) | B23: 210 | D23: Implied Equity Value (₹ cr) | E23: =E22-B23 | G23: Implied Equity Value (₹ cr) | H23: =H22-B23
A24: Shares Outstanding (cr) | B24: 6 | D24: Implied Price per Share (₹) | E24: =(E23)/(B24) | G24: Implied Price per Share (₹) | H24: =(H23)/(B24)
A26: SECTION D — Checks
A27: Check 1: At least 3 deals included | B27: =IF(E17>=3,"PASS","FAIL") | D27: Case Status | E27: =IF(AND(B27="PASS",B28="PASS",B29="PASS"),"PASS","FAIL")
A28: Check 2: No DIV/0! in EV/EBITDA | B28: =IF(COUNTIF(N7:N14,"#DIV/0!")=0,"PASS","FAIL")
A29: Check 3: Included stakes between 0% and 100% | B29: =IF(SUMPRODUCT(--(J7:J14=1),--((E7:E14<=0)+(E7:E14>1)))=0,"PASS","FAIL")
A31: ⬅ Back to INDEX

Sheet CASE_3_AvgVsMedian_Outliers
A1: CASE 3 — Average vs Median Multiples (Outliers)
N2: ⬅ Back to INDEX
A3: Learning point: Average can be pulled by high-multiple outliers; median is more robust.
A5: SECTION A — Comparable Transactions (Inputs)
A6: Deal Ref | B6: Acquirer | C6: Target | D6: Deal Type | E6: Stake % | F6: Deal Value (₹ cr) | G6: Revenue (₹ cr) | H6: EBITDA (₹ cr) | I6: Net Debt (₹ cr) | J6: Include? (0/1) | K6: Equity Value @100% (₹ cr) | L6: Enterprise Value (₹ cr) | M6: EV/Revenue | N6: EV/EBITDA
A7: D01 | B7: Sun Pharma | C7: Medigen Labs Pvt. Ltd. | D7: Strategic | E7: 1 | F7: 2100 | G7: 1600 | H7: 210 | I7: 420 | J7: 1 | K7: =IF(J7=1,F7/(E7),"") | L7: =IF(J7=1,K7+I7,"") | M7: =IF(J7=1,L7/G7,"") | N7: =IF(J7=1,L7/H7,"")
A8: D02 | B8: Pfizer India | C8: CureWell Pharma Pvt. Ltd. | D8: MNC Acquisition | E8: 1 | F8: 3800 | G8: 2400 | H8: 260 | I8: 500 | J8: 1 | K8: =IF(J8=1,F8/(E8),"") | L8: =IF(J8=1,K8+I8,"") | M8: =IF(J8=1,L8/G8,"") | N8: =IF(J8=1,L8/H8,"")
A9: D03 | B9: Cipla Ltd. | C9: BioHealth Pvt. Ltd. | D9: Strategic | E9: 1 | F9: 1750 | G9: 1350 | H9: 180 | I9: 360 | J9: 1 | K9: =IF(J9=1,F9/(E9),"") | L9: =IF(J9=1,K9+I9,"") | M9: =IF(J9=1,L9/G9,"") | N9: =IF(J9=1,L9/H9,"")
A10: D04 | B10: Novartis India | C10: LifeCare Pharma Pvt. Ltd. | D10: MNC Acquisition | E10: 1 | F10: 4200 | G10: 2700 | H10: 280 | I10: 540 | J10: 1 | K10: =IF(J10=1,F10/(E10),"") | L10: =IF(J10=1,K10+I10,"") | M10: =IF(J10=1,L10/G10,"") | N10: =IF(J10=1,L10/H10,"")
A11: D05 | B11: Dr. Reddy’s Labs | C11: PureDrugs Pvt. Ltd. | D11: Strategic | E11: 1 | F11: 2300 | G11: 1800 | H11: 220 | I11: 410 | J11: 1 | K11: =IF(J11=1,F11/(E11),"") | L11: =IF(J11=1,K11+I11,"") | M11: =IF(J11=1,L11/G11,"") | N11: =IF(J11=1,L11/H11,"")
A12: D06 | B12: Lupin Ltd. | C12: WellGen Pharma Pvt. Ltd. | D12: Strategic | E12: 1 | F12: 1600 | G12: 1250 | H12: 160 | I12: 300 | J12: 1 | K12: =IF(J12=1,F12/(E12),"") | L12: =IF(J12=1,K12+I12,"") | M12: =IF(J12=1,L12/G12,"") | N12: =IF(J12=1,L12/H12,"")
A13: D07 | B13: Aurobindo Pharma | C13: NovaCure Pvt. Ltd. | D13: Strategic | E13: 1 | F13: 2050 | G13: 1550 | H13: 200 | I13: 390 | J13: 1 | K13: =IF(J13=1,F13/(E13),"") | L13: =IF(J13=1,K13+I13,"") | M13: =IF(J13=1,L13/G13,"") | N13: =IF(J13=1,L13/H13,"")
A14: D08 | B14: Glenmark Pharma | C14: Healix Pharma Pvt. Ltd. | D14: Strategic | E14: 1 | F14: 1900 | G14: 1450 | H14: 190 | I14: 350 | J14: 1 | K14: =IF(J14=1,F14/(E14),"") | L14: =IF(J14=1,K14+I14,"") | M14: =IF(J14=1,L14/G14,"") | N14: =IF(J14=1,L14/H14,"")
A16: SECTION B — Descriptive Statistics (Selected Deals Only)
A17: Average EV/EBITDA | B17: =AVERAGEIF(J7:J14,1,N7:N14) | D17: Included deals (count) | E17: =COUNTIF(J7:J14,1)
A18: Median EV/EBITDA
A20: SECTION C — Target Company Valuation (Using EV/EBITDA)
A21: Target Company | B21: GHI Pharma Pvt. Ltd. | D21: Using Average Multiple | G21: Using Median Multiple
A22: Target EBITDA (₹ cr) | B22: 140 | D22: Implied EV (₹ cr) | E22: =B17*B22 | G22: Implied EV (₹ cr) | H22: =B18*B22
A23: Target Net Debt (₹ cr) | B23: 300 | D23: Implied Equity Value (₹ cr) | E23: =E22-B23 | G23: Implied Equity Value (₹ cr) | H23: =H22-B23
A24: Shares Outstanding (cr) | B24: 10 | D24: Implied Price per Share (₹) | E24: =(E23)/(B24) | G24: Implied Price per Share (₹) | H24: =(H23)/(B24)
A26: SECTION D — Checks
A27: Check 1: At least 3 deals included | B27: =IF(E17>=3,"PASS","FAIL") | D27: Case Status | E27: =IF(AND(B27="PASS",B28="PASS",B29="PASS"),"PASS","FAIL")
A28: Check 2: No DIV/0! in EV/EBITDA | B28: =IF(COUNTIF(N7:N14,"#DIV/0!")=0,"PASS","FAIL")
A29: Check 3: Included stakes between 0% and 100% | B29: =IF(SUMPRODUCT(--(J7:J14=1),--((E7:E14<=0)+(E7:E14>1)))=0,"PASS","FAIL")
A31: ⬅ Back to INDEX

Sheet CASE_4_PartialStake_Normalizati
A1: CASE 4 — Normalising Partial Stake Deals to 100% Equity Value
N2: ⬅ Back to INDEX
A3: Learning point: Scale partial stake deal values to 100% equity before computing EV multiples.
A5: SECTION A — Comparable Transactions (Inputs)
A6: Deal Ref | B6: Acquirer | C6: Target | D6: Deal Type | E6: Stake % | F6: Deal Value (₹ cr) | G6: Revenue (₹ cr) | H6: EBITDA (₹ cr) | I6: Net Debt (₹ cr) | J6: Include? (0/1) | K6: Equity Value @100% (₹ cr) | L6: Enterprise Value (₹ cr) | M6: EV/Revenue | N6: EV/EBITDA
A7: D01 | B7: L&T Ltd. | C7: Eastern BuildCo Pvt. Ltd. | D7: Majority Stake | E7: 0.7 | F7: 1400 | G7: 2100 | H7: 260 | I7: 780 | J7: 1 | K7: =IF(J7=1,F7/(E7),"") | L7: =IF(J7=1,K7+I7,"") | M7: =IF(J7=1,L7/G7,"") | N7: =IF(J7=1,L7/H7,"")
A8: D02 | B8: GMR Group | C8: Skyline Infra Pvt. Ltd. | D8: Majority Stake | E8: 0.6 | F8: 1800 | G8: 2400 | H8: 300 | I8: 850 | J8: 1 | K8: =IF(J8=1,F8/(E8),"") | L8: =IF(J8=1,K8+I8,"") | M8: =IF(J8=1,L8/G8,"") | N8: =IF(J8=1,L8/H8,"")
A9: D03 | B9: Adani Infra | C9: MetroWorks Pvt. Ltd. | D9: Full Acquisition | E9: 1 | F9: 2200 | G9: 2800 | H9: 340 | I9: 920 | J9: 1 | K9: =IF(J9=1,F9/(E9),"") | L9: =IF(J9=1,K9+I9,"") | M9: =IF(J9=1,L9/G9,"") | N9: =IF(J9=1,L9/H9,"")
A10: D04 | B10: IRB Infrastructure | C10: RoadLink Pvt. Ltd. | D10: Majority Stake | E10: 0.55 | F10: 1250 | G10: 1900 | H10: 230 | I10: 700 | J10: 1 | K10: =IF(J10=1,F10/(E10),"") | L10: =IF(J10=1,K10+I10,"") | M10: =IF(J10=1,L10/G10,"") | N10: =IF(J10=1,L10/H10,"")
A11: D05 | B11: NCC Ltd. | C11: PowerBuild Pvt. Ltd. | D11: Full Acquisition | E11: 1 | F11: 2600 | G11: 3100 | H11: 380 | I11: 1050 | J11: 1 | K11: =IF(J11=1,F11/(E11),"") | L11: =IF(J11=1,K11+I11,"") | M11: =IF(J11=1,L11/G11,"") | N11: =IF(J11=1,L11/H11,"")
A12: D06 | B12: Dilip Buildcon | C12: UrbanConstruct Pvt. Ltd. | D12: Majority Stake | E12: 0.65 | F12: 1500 | G12: 2200 | H12: 270 | I12: 810 | J12: 1 | K12: =IF(J12=1,F12/(E12),"") | L12: =IF(J12=1,K12+I12,"") | M12: =IF(J12=1,L12/G12,"") | N12: =IF(J12=1,L12/H12,"")
A13: D07 | B13: Ashoka Buildcon | C13: Highway Systems Pvt. Ltd. | D13: Majority Stake | E13: 0.75 | F13: 1350 | G13: 2000 | H13: 250 | I13: 760 | J13: 1 | K13: =IF(J13=1,F13/(E13),"") | L13: =IF(J13=1,K13+I13,"") | M13: =IF(J13=1,L13/G13,"") | N13: =IF(J13=1,L13/H13,"")
A14: D08 | B14: Tata Projects | C14: InfraCore Pvt. Ltd. | D14: Full Acquisition | E14: 1 | F14: 2400 | G14: 2900 | H14: 360 | I14: 980 | J14: 1 | K14: =IF(J14=1,F14/(E14),"") | L14: =IF(J14=1,K14+I14,"") | M14: =IF(J14=1,L14/G14,"") | N14: =IF(J14=1,L14/H14,"")
A16: SECTION B — Descriptive Statistics (Selected Deals Only)
A17: Average EV/EBITDA | B17: =AVERAGEIF(J7:J14,1,N7:N14) | D17: Included deals (count) | E17: =COUNTIF(J7:J14,1)
A18: Median EV/EBITDA
A20: SECTION C — Target Company Valuation (Using EV/EBITDA)
A21: Target Company | B21: MNO Projects Pvt. Ltd. | D21: Using Average Multiple | G21: Using Median Multiple
A22: Target EBITDA (₹ cr) | B22: 220 | D22: Implied EV (₹ cr) | E22: =B17*B22 | G22: Implied EV (₹ cr) | H22: =B18*B22
A23: Target Net Debt (₹ cr) | B23: 650 | D23: Implied Equity Value (₹ cr) | E23: =E22-B23 | G23: Implied Equity Value (₹ cr) | H23: =H22-B23
A24: Shares Outstanding (cr) | B24: 15 | D24: Implied Price per Share (₹) | E24: =(E23)/(B24) | G24: Implied Price per Share (₹) | H24: =(H23)/(B24)
A26: SECTION D — Checks
A27: Check 1: At least 3 deals included | B27: =IF(E17>=3,"PASS","FAIL") | D27: Case Status | E27: =IF(AND(B27="PASS",B28="PASS",B29="PASS"),"PASS","FAIL")
A28: Check 2: No DIV/0! in EV/EBITDA | B28: =IF(COUNTIF(N7:N14,"#DIV/0!")=0,"PASS","FAIL")
A29: Check 3: Included stakes between 0% and 100% | B29: =IF(SUMPRODUCT(--(J7:J14=1),--((E7:E14<=0)+(E7:E14>1)))=0,"PASS","FAIL")
A31: ⬅ Back to INDEX

Sheet CASE_5_Judgment_Integrated
A1: CASE 5 — Integrated PTM (Judgment + Selection)
N2: ⬅ Back to INDEX
A3: Learning point: PTM requires judgment: select deals, compute multiples, interpret outputs.
A5: SECTION A — Comparable Transactions (Inputs)
A6: Deal Ref | B6: Acquirer | C6: Target | D6: Deal Type | E6: Stake % | F6: Deal Value (₹ cr) | G6: Revenue (₹ cr) | H6: EBITDA (₹ cr) | I6: Net Debt (₹ cr) | J6: Include? (0/1) | K6: Equity Value @100% (₹ cr) | L6: Enterprise Value (₹ cr) | M6: EV/Revenue | N6: EV/EBITDA
A7: D01 | B7: Hindustan Unilever | C7: FreshHarvest Foods Pvt. Ltd. | D7: Premium Brand | E7: 1 | F7: 1600 | G7: 1450 | H7: 170 | I7: 220 | J7: 1 | K7: =IF(J7=1,F7/(E7),"") | L7: =IF(J7=1,K7+I7,"") | M7: =IF(J7=1,L7/G7,"") | N7: =IF(J7=1,L7/H7,"")
A8: D02 | B8: ITC Ltd. | C8: DailyGrain Foods Pvt. Ltd. | D8: Distressed | E8: 1 | F8: 1100 | G8: 1200 | H8: 140 | I8: 190 | J8: 1 | K8: =IF(J8=1,F8/(E8),"") | L8: =IF(J8=1,K8+I8,"") | M8: =IF(J8=1,L8/G8,"") | N8: =IF(J8=1,L8/H8,"")
A9: D03 | B9: Nestlé India | C9: NutriChoice Pvt. Ltd. | D9: Strategic | E9: 1 | F9: 1900 | G9: 1650 | H9: 185 | I9: 260 | J9: 1 | K9: =IF(J9=1,F9/(E9),"") | L9: =IF(J9=1,K9+I9,"") | M9: =IF(J9=1,L9/G9,"") | N9: =IF(J9=1,L9/H9,"")
A10: D04 | B10: Britannia Industries | C10: RoyalTaste Foods Pvt. Ltd. | D10: Premium Brand | E10: 1 | F10: 2300 | G10: 1900 | H10: 210 | I10: 300 | J10: 1 | K10: =IF(J10=1,F10/(E10),"") | L10: =IF(J10=1,K10+I10,"") | M10: =IF(J10=1,L10/G10,"") | N10: =IF(J10=1,L10/H10,"")
A11: D05 | B11: Blackstone India | C11: FoodBasket Pvt. Ltd. | D11: Leveraged Buyout (LBO) | E11: 0.75 | F11: 1250 | G11: 1300 | H11: 150 | I11: 200 | J11: 1 | K11: =IF(J11=1,F11/(E11),"") | L11: =IF(J11=1,K11+I11,"") | M11: =IF(J11=1,L11/G11,"") | N11: =IF(J11=1,L11/H11,"")
A12: D06 | B12: Marico Ltd. | C12: HomeDelights Pvt. Ltd. | D12: Strategic | E12: 1 | F12: 1450 | G12: 1400 | H12: 165 | I12: 230 | J12: 1 | K12: =IF(J12=1,F12/(E12),"") | L12: =IF(J12=1,K12+I12,"") | M12: =IF(J12=1,L12/G12,"") | N12: =IF(J12=1,L12/H12,"")
A13: D07 | B13: Dabur India | C13: NatureFoods Pvt. Ltd. | D13: Strategic | E13: 1 | F13: 2100 | G13: 1800 | H13: 195 | I13: 280 | J13: 1 | K13: =IF(J13=1,F13/(E13),"") | L13: =IF(J13=1,K13+I13,"") | M13: =IF(J13=1,L13/G13,"") | N13: =IF(J13=1,L13/H13,"")
A14: D08 | B14: Godrej Consumer | C14: TasteHub Pvt. Ltd. | D14: Majority Stake | E14: 0.6 | F14: 1300 | G14: 1350 | H14: 155 | I14: 210 | J14: 1 | K14: =IF(J14=1,F14/(E14),"") | L14: =IF(J14=1,K14+I14,"") | M14: =IF(J14=1,L14/G14,"") | N14: =IF(J14=1,L14/H14,"")
A16: SECTION B — Descriptive Statistics (Selected Deals Only)
A17: Average EV/EBITDA | B17: =AVERAGEIF(J7:J14,1,N7:N14) | D17: Included deals (count) | E17: =COUNTIF(J7:J14,1)
A18: Median EV/EBITDA
A20: SECTION C — Target Company Valuation (Using EV/EBITDA)
A21: Target Company | B21: UVW Foods Pvt. Ltd. | D21: Using Average Multiple | G21: Using Median Multiple
A22: Target EBITDA (₹ cr) | B22: 125 | D22: Implied EV (₹ cr) | E22: =B17*B22 | G22: Implied EV (₹ cr) | H22: =B18*B22
A23: Target Net Debt (₹ cr) | B23: 180 | D23: Implied Equity Value (₹ cr) | E23: =E22-B23 | G23: Implied Equity Value (₹ cr) | H23: =H22-B23
A24: Shares Outstanding (cr) | B24: 8 | D24: Implied Price per Share (₹) | E24: =(E23)/(B24) | G24: Implied Price per Share (₹) | H24: =(H23)/(B24)
A26: SECTION D — Checks
A27: Check 1: At least 3 deals included | B27: =IF(E17>=3,"PASS","FAIL") | D27: Case Status | E27: =IF(AND(B27="PASS",B28="PASS",B29="PASS"),"PASS","FAIL")
A28: Check 2: No DIV/0! in EV/EBITDA | B28: =IF(COUNTIF(N7:N14,"#DIV/0!")=0,"PASS","FAIL")
A29: Check 3: Included stakes between 0% and 100% | B29: =IF(SUMPRODUCT(--(J7:J14=1),--((E7:E14<=0)+(E7:E14>1)))=0,"PASS","FAIL")
A31: ⬅ Back to INDEX

Sheet CHECKS_Summary
A1: Workbook Checks Summary
A3: Case | B3: Sheet (click to open) | C3: Included Deals | D3: Avg EV/EBITDA | E3: Median EV/EBITDA | F3: Status
A4: Case 1 | B4: CASE_1_ControlPremium_100pct | C4: =CASE_1_ControlPremium_100pct!E17 | D4: =CASE_1_ControlPremium_100pct!B17 | E4: =CASE_1_ControlPremium_100pct!B18 | F4: =CASE_1_ControlPremium_100pct!E27
A5: Case 2 | B5: CASE_2_DealSelection_Include01 | C5: =CASE_2_DealSelection_Include01!E17 | D5: =CASE_2_DealSelection_Include01!B17 | E5: =CASE_2_DealSelection_Include01!B18 | F5: =CASE_2_DealSelection_Include01!E27
A6: Case 3 | B6: CASE_3_AvgVsMedian_Outliers | C6: =CASE_3_AvgVsMedian_Outliers!E17 | D6: =CASE_3_AvgVsMedian_Outliers!B17 | E6: =CASE_3_AvgVsMedian_Outliers!B18 | F6: =CASE_3_AvgVsMedian_Outliers!E27
A7: Case 4 | B7: CASE_4_PartialStake_Normalization | C7: =CASE_4_PartialStake_Normalizati!E17 | D7: =CASE_4_PartialStake_Normalizati!B17 | E7: =CASE_4_PartialStake_Normalizati!B18 | F7: =CASE_4_PartialStake_Normalizati!E27
A8: Case 5 | B8: CASE_5_Judgment_Integrated | C8: =CASE_5_Judgment_Integrated!E17 | D8: =CASE_5_Judgment_Integrated!B17 | E8: =CASE_5_Judgment_Integrated!B18 | F8: =CASE_5_Judgment_Integrated!E27
A12: Unit note: Deal values, Revenue, EBITDA, Net Debt are in ₹ crore; Shares Outstanding is in crore shares.
